tinypy/__init__.py
tinypy/main.py
tinypy/t_csv.py
tinypy/t_json.py
tinypy/terminal.py
tinypy-0.2.2.dist-info/LICENSE
tinypy-0.2.2.dist-info/METADATA
tinypy-0.2.2.dist-info/WHEEL
tinypy-0.2.2.dist-info/entry_points.txt
tinypy-0.2.2.dist-info/top_level.txt
tinypy-0.2.2.dist-info/RECORD
