Metadata-Version: 2.1
Name: tinypy
Version: 0.2.2
Summary: Tinypy is a collection of small Python functions and classes which make common patterns shorter and faster.
Home-page: https://github.com/arashyeganeh/tinypy
Download-URL: https://github.com/arashyeganeh/tinypy/releases/tag/0.2.2
Author: Arash Yeganeh
License: MIT
Project-URL: Bug Reports, https://github.com/arashyeganeh/tinypy/issues
Project-URL: Source, https://github.com/arashyeganeh/tinypy
Project-URL: LinkedIn, https://www.linkedin.com/in/arash-yeganeh
Keywords: utils,tiny,lightweight,json,convert json,csv,convert csv
Classifier: Development Status :: 5 - Production/Stable
Classifier: Intended Audience :: Developers
Classifier: Intended Audience :: End Users/Desktop
Classifier: Intended Audience :: System Administrators
Classifier: Natural Language :: English
Classifier: License :: OSI Approved :: MIT License
Classifier: Programming Language :: Python :: 3.6
Classifier: Programming Language :: Python :: 3.7
Classifier: Programming Language :: Python :: 3.8
Classifier: Programming Language :: Python :: 3.9
Classifier: Programming Language :: Python :: 3.10
Classifier: Programming Language :: Python :: 3.11
Classifier: Topic :: Utilities
Requires-Python: >=3
License-File: LICENSE
